winui3/_winui3_microsoft_windows_ai_machinelearning.cp311-win_arm64.pyd
winui3/_winui3_microsoft_windows_ai_machinelearning.pyi
winui3/microsoft/windows/ai/machinelearning/__init__.py
winui3/microsoft/windows/ai/machinelearning/py.typed
wasdk_microsoft_windows_ai_machinelearning-1.8.260101001.dist-info/METADATA
wasdk_microsoft_windows_ai_machinelearning-1.8.260101001.dist-info/WHEEL
wasdk_microsoft_windows_ai_machinelearning-1.8.260101001.dist-info/top_level.txt
wasdk_microsoft_windows_ai_machinelearning-1.8.260101001.dist-info/RECORD
